reqman4/__init__.py
reqman4/__main__.py
reqman4/common.py
reqman4/compat.py
reqman4/ehttp.py
reqman4/env.py
reqman4/main.py
reqman4/output.py
reqman4/scenario.py
reqman4/tool.py
reqman4-0.5.7.dist-info/WHEEL
reqman4-0.5.7.dist-info/entry_points.txt
reqman4-0.5.7.dist-info/METADATA
reqman4-0.5.7.dist-info/RECORD
