Metadata-Version: 2.3
Name: reqman4
Version: 0.5.7
Summary: reqman4 (prototype), command 'rq' 
Requires-Dist: click>=8.2.1
Requires-Dist: colorama>=0.4.6
Requires-Dist: httpx>=0.28.1
Requires-Dist: pyjwt>=2.10.1
Requires-Dist: python-dotenv>=1.1.1
Requires-Dist: ruamel-yaml>=0.18.15
Requires-Python: >=3.11
Project-URL: Homepage, https://github.com/manatlan/reqman4
Project-URL: Issues, https://github.com/manatlan/reqman4/issues
Project-URL: Repository, https://github.com/manatlan/reqman4
